MANIFEST.in
hathilda.py
requirements.txt
setup.py
hathilda.egg-info/PKG-INFO
hathilda.egg-info/SOURCES.txt
hathilda.egg-info/dependency_links.txt
hathilda.egg-info/requires.txt
hathilda.egg-info/top_level.txt