Metadata-Version: 1.0
Name: hathilda
Version: 0.0.12
Summary: Turn HathiTrust Data into JSON-LD
Home-page: http://github.com/umd_mith/hathild
Author: Ed Summers
Author-email: ehs@pobox.com
License: UNKNOWN
Platform: UNKNOWN
